{"sections":{"61b7b6d5-6f8c-4ac8-b0a5-45de20403fba":{"type":"slideshow","blocks":{"template--14433861042222__61b7b6d5-6f8c-4ac8-b0a5-45de20403fba-1665048192ef74f4bb-1":{"type":"hero","settings":{"top_subheading":"","subheading_color":"#ffffff","title":"","title_size":70,"heading_color":"#ffffff","subheading":"","optional_subheading_color":"#ffffff","link":"https:\/\/forms.gle\/4HY1xXnsDe3v6skv7","link_text":"","link_2":"","link_text_2":"","color_accent":"#ffffff","text_align":"vertical-center horizontal-center","image":"shopify:\/\/shop_images\/Group_415.jpg","image_mobile":"shopify:\/\/shop_images\/Trail_page_Mobile_1c6ef722-21fc-4dd2-9197-4c496e68b18a.jpg","overlay_opacity":0,"focal_point":"center center"}}},"block_order":["template--14433861042222__61b7b6d5-6f8c-4ac8-b0a5-45de20403fba-1665048192ef74f4bb-1"],"settings":{"full_width":true,"desktop_size":0,"mobile_size":0,"style":"arrows","autoplay":true,"autoplay_speed":7}},"e36fb07e-4e6a-46f6-b17e-eb934a446b1a":{"type":"slideshow","blocks":{"ff54b12a-a84a-4310-8baf-7aa68519a29c":{"type":"hero","settings":{"top_subheading":"","subheading_color":"#ffffff","title":"","title_size":70,"heading_color":"#ffffff","subheading":"","optional_subheading_color":"#ffffff","link":"shopify:\/\/collections\/bare-anatomy-store","link_text":"","link_2":"","link_text_2":"","color_accent":"#ffffff","text_align":"vertical-bottom horizontal-left","image":"shopify:\/\/shop_images\/Trail_page_desktop_copy_3.jpg","image_mobile":"shopify:\/\/shop_images\/Trail_page_Mobile_copy_3.jpg","overlay_opacity":0,"focal_point":"center center"}}},"block_order":["ff54b12a-a84a-4310-8baf-7aa68519a29c"],"settings":{"full_width":true,"desktop_size":0,"mobile_size":0,"style":"minimal","autoplay":false,"autoplay_speed":7}},"ef396111-e070-4066-96f4-762988c5625e":{"type":"slideshow","blocks":{"template--14433861042222__ef396111-e070-4066-96f4-762988c5625e-1666252428410e1dac-0":{"type":"hero","settings":{"top_subheading":"","subheading_color":"#ffffff","title":"","title_size":70,"heading_color":"#ffffff","subheading":"","optional_subheading_color":"#ffffff","link":"shopify:\/\/collections\/chemist-at-play","link_text":"","link_2":"","link_text_2":"","color_accent":"#ffffff","text_align":"vertical-bottom horizontal-left","image":"shopify:\/\/shop_images\/Group_429_1.png","image_mobile":"shopify:\/\/shop_images\/Group_429-3.png","overlay_opacity":0,"focal_point":"center center"}},"template--14433861042222__ef396111-e070-4066-96f4-762988c5625e-1666252428410e1dac-1":{"type":"hero","disabled":true,"settings":{"top_subheading":"","subheading_color":"#ffffff","title":"<p>Make an Impact<\/p>","title_size":70,"heading_color":"#ffffff","subheading":"Supports multiple text alignments and mobile-specific images.","optional_subheading_color":"#ffffff","link":"","link_text":"Optional button","link_2":"","link_text_2":"","color_accent":"#ffffff","text_align":"vertical-center horizontal-center","overlay_opacity":0,"focal_point":"center center"}}},"block_order":["template--14433861042222__ef396111-e070-4066-96f4-762988c5625e-1666252428410e1dac-0","template--14433861042222__ef396111-e070-4066-96f4-762988c5625e-1666252428410e1dac-1"],"settings":{"full_width":true,"desktop_size":0,"mobile_size":0,"style":"arrows","autoplay":true,"autoplay_speed":7}},"42be135c-fd61-44bd-899b-e042a16dfc9f":{"type":"slideshow","blocks":{"template--14433861042222__42be135c-fd61-44bd-899b-e042a16dfc9f-1666252428410e1dac-0":{"type":"hero","settings":{"top_subheading":"","subheading_color":"#ffffff","title":"","title_size":70,"heading_color":"#ffffff","subheading":"","optional_subheading_color":"#ffffff","link":"https:\/\/forms.gle\/4HY1xXnsDe3v6skv7","link_text":"","link_2":"","link_text_2":"","color_accent":"#ffffff","text_align":"vertical-bottom horizontal-left","image":"shopify:\/\/shop_images\/Frame_18_a0ada209-8b1e-464f-ab47-a61349449461.png","image_mobile":"shopify:\/\/shop_images\/Group_429-2.png","overlay_opacity":0,"focal_point":"center center"}},"template--14433861042222__42be135c-fd61-44bd-899b-e042a16dfc9f-1666252428410e1dac-1":{"type":"hero","disabled":true,"settings":{"top_subheading":"","subheading_color":"#ffffff","title":"","title_size":70,"heading_color":"#ffffff","subheading":"","optional_subheading_color":"#ffffff","link":"","link_text":"","link_2":"","link_text_2":"","color_accent":"#ffffff","text_align":"vertical-center horizontal-center","overlay_opacity":0,"focal_point":"center center"}}},"block_order":["template--14433861042222__42be135c-fd61-44bd-899b-e042a16dfc9f-1666252428410e1dac-0","template--14433861042222__42be135c-fd61-44bd-899b-e042a16dfc9f-1666252428410e1dac-1"],"settings":{"full_width":true,"desktop_size":0,"mobile_size":0,"style":"arrows","autoplay":true,"autoplay_speed":7}},"1ee1515d-d0e2-4cd5-94e0-8f98b2255e07":{"type":"slideshow","blocks":{"template--14460510863406__1ee1515d-d0e2-4cd5-94e0-8f98b2255e07-166762432308a91189-0":{"type":"hero","settings":{"top_subheading":"","subheading_color":"#ffffff","title":"","title_size":70,"heading_color":"#ffffff","subheading":"","optional_subheading_color":"#ffffff","link":"","link_text":"","link_2":"","link_text_2":"","color_accent":"#ffffff","text_align":"vertical-bottom horizontal-left","image":"shopify:\/\/shop_images\/Group_430.png","image_mobile":"shopify:\/\/shop_images\/Group_429-1.png","overlay_opacity":0,"focal_point":"center center"}},"template--14460510863406__1ee1515d-d0e2-4cd5-94e0-8f98b2255e07-166762432308a91189-1":{"type":"hero","disabled":true,"settings":{"top_subheading":"","subheading_color":"#ffffff","title":"<p>Make an Impact<\/p>","title_size":70,"heading_color":"#ffffff","subheading":"Supports multiple text alignments and mobile-specific images.","optional_subheading_color":"#ffffff","link":"","link_text":"Optional button","link_2":"","link_text_2":"","color_accent":"#ffffff","text_align":"vertical-center horizontal-center","overlay_opacity":0,"focal_point":"center center"}}},"block_order":["template--14460510863406__1ee1515d-d0e2-4cd5-94e0-8f98b2255e07-166762432308a91189-0","template--14460510863406__1ee1515d-d0e2-4cd5-94e0-8f98b2255e07-166762432308a91189-1"],"settings":{"full_width":true,"desktop_size":0,"mobile_size":0,"style":"arrows","autoplay":true,"autoplay_speed":7}},"763b373b-ec6a-4674-a5ec-23d669741f9e":{"type":"slideshow","blocks":{"template--14460510863406__763b373b-ec6a-4674-a5ec-23d669741f9e-166762432308a91189-0":{"type":"hero","settings":{"top_subheading":"","subheading_color":"#ffffff","title":"","title_size":70,"heading_color":"#ffffff","subheading":"","optional_subheading_color":"#ffffff","link":"","link_text":"","link_2":"","link_text_2":"","color_accent":"#ffffff","text_align":"vertical-bottom horizontal-left","image":"shopify:\/\/shop_images\/Group_423.png","image_mobile":"shopify:\/\/shop_images\/Group_429.png","overlay_opacity":0,"focal_point":"center center"}},"template--14460510863406__763b373b-ec6a-4674-a5ec-23d669741f9e-166762432308a91189-1":{"type":"hero","disabled":true,"settings":{"top_subheading":"","subheading_color":"#ffffff","title":"<p>Make an Impact<\/p>","title_size":70,"heading_color":"#ffffff","subheading":"Supports multiple text alignments and mobile-specific images.","optional_subheading_color":"#ffffff","link":"","link_text":"Optional button","link_2":"","link_text_2":"","color_accent":"#ffffff","text_align":"vertical-center horizontal-center","overlay_opacity":0,"focal_point":"center center"}}},"block_order":["template--14460510863406__763b373b-ec6a-4674-a5ec-23d669741f9e-166762432308a91189-0","template--14460510863406__763b373b-ec6a-4674-a5ec-23d669741f9e-166762432308a91189-1"],"settings":{"full_width":true,"desktop_size":0,"mobile_size":0,"style":"arrows","autoplay":true,"autoplay_speed":7}},"574a3625-98e6-49a1-a027-c2ac434584e6":{"type":"advanced-content","blocks":{"template--14433861042222__574a3625-98e6-49a1-a027-c2ac434584e6-16662510074734ecb5-1":{"type":"liquid","settings":{"code":"<h2><br><br><center><span style=\"font-size:19px\"margin:0;\">Our Story<\/h2>\n\n\n<center><p style=\"font-size:13px;line-height:1.5;\">Back in 2019, Innovist launched its first brand, <br>\nBare Anatomy, which offered customized hair care. <br> Since day 1, our focus has been on formulating scientific, data driven, effective, and customer centric <br> personal care products.\n\n<br><br>\nInnovist currently owns three brands<br><br><\/font>","width":"100%","alignment":"center"}},"template--14433861042222__574a3625-98e6-49a1-a027-c2ac434584e6-16662510074734ecb5-0":{"type":"image","settings":{"image":"shopify:\/\/shop_images\/Group_1276_0ef62c00-bda7-4990-acc6-9bc7af785ab0.png","link":"","width":"100%","alignment":"center"}},"52c15f0d-9b5b-4a1a-8aa0-bc531dc7da37":{"type":"liquid","settings":{"code":"<center><p style=\"font-size:13px;line-height:1.5;\">All three brands have the same DNA <br>\n<b>Clean  |  Transparent  |  Science<\/b>\n\n<br><br>\nInnovist is one of the only startups in India that <br> started out by first building a Research Lab and a Manufacturing Facility.<br><br><\/font>","width":"100%","alignment":"center"}}},"block_order":["template--14433861042222__574a3625-98e6-49a1-a027-c2ac434584e6-16662510074734ecb5-1","template--14433861042222__574a3625-98e6-49a1-a027-c2ac434584e6-16662510074734ecb5-0","52c15f0d-9b5b-4a1a-8aa0-bc531dc7da37"],"disabled":true,"settings":{"full_width":false,"space_around":true}},"29dc291e-8037-4113-85f5-d18cdba5526b":{"type":"advanced-content","blocks":{"template--14433861042222__29dc291e-8037-4113-85f5-d18cdba5526b-1666252427d4f85f79-0":{"type":"image","disabled":true,"settings":{"link":"","width":"50%","alignment":"center"}},"template--14433861042222__29dc291e-8037-4113-85f5-d18cdba5526b-1666252427d4f85f79-1":{"type":"liquid","settings":{"code":"<h2><br><br><center><span style=\"font-size:18px\"margin:0;\">Explore Our Award-Winnning Brands<\/h2>","width":"100%","alignment":"center"}}},"block_order":["template--14433861042222__29dc291e-8037-4113-85f5-d18cdba5526b-1666252427d4f85f79-0","template--14433861042222__29dc291e-8037-4113-85f5-d18cdba5526b-1666252427d4f85f79-1"],"disabled":true,"settings":{"full_width":false,"space_around":true}},"2d7bd09b-199e-48da-a0ce-142c9912adfc":{"type":"advanced-content","blocks":{"template--14433861042222__2d7bd09b-199e-48da-a0ce-142c9912adfc-1666252427d4f85f79-0":{"type":"image","disabled":true,"settings":{"link":"","width":"50%","alignment":"center"}},"template--14433861042222__2d7bd09b-199e-48da-a0ce-142c9912adfc-1666252427d4f85f79-1":{"type":"liquid","settings":{"code":"<br><br>","width":"50%","alignment":"center"}}},"block_order":["template--14433861042222__2d7bd09b-199e-48da-a0ce-142c9912adfc-1666252427d4f85f79-0","template--14433861042222__2d7bd09b-199e-48da-a0ce-142c9912adfc-1666252427d4f85f79-1"],"disabled":true,"settings":{"full_width":false,"space_around":true}},"82a03487-ea3a-45b4-b3bf-6bbb38ba0887":{"type":"advanced-content","blocks":{"template--14433861042222__82a03487-ea3a-45b4-b3bf-6bbb38ba0887-1666252427d4f85f79-0":{"type":"image","disabled":true,"settings":{"link":"","width":"50%","alignment":"center"}},"template--14433861042222__82a03487-ea3a-45b4-b3bf-6bbb38ba0887-1666252427d4f85f79-1":{"type":"liquid","settings":{"code":"<br><br>","width":"50%","alignment":"center"}}},"block_order":["template--14433861042222__82a03487-ea3a-45b4-b3bf-6bbb38ba0887-1666252427d4f85f79-0","template--14433861042222__82a03487-ea3a-45b4-b3bf-6bbb38ba0887-1666252427d4f85f79-1"],"disabled":true,"settings":{"full_width":false,"space_around":true}},"8276f75f-e3fe-4298-8c89-1a278c83682a":{"type":"advanced-content","blocks":{"template--14433861042222__8276f75f-e3fe-4298-8c89-1a278c83682a-1666252427d4f85f79-1":{"type":"liquid","settings":{"code":"<h2><br><br><br><center><span style=\"font-size:18px\"margin:0;\">Inside Innovist<\/h2>","width":"100%","alignment":"center"}},"template--14433861042222__8276f75f-e3fe-4298-8c89-1a278c83682a-1666252427d4f85f79-0":{"type":"image","disabled":true,"settings":{"link":"","width":"50%","alignment":"center"}}},"block_order":["template--14433861042222__8276f75f-e3fe-4298-8c89-1a278c83682a-1666252427d4f85f79-1","template--14433861042222__8276f75f-e3fe-4298-8c89-1a278c83682a-1666252427d4f85f79-0"],"disabled":true,"settings":{"full_width":false,"space_around":true}},"main":{"type":"main-page","disabled":true,"settings":{}}},"order":["61b7b6d5-6f8c-4ac8-b0a5-45de20403fba","e36fb07e-4e6a-46f6-b17e-eb934a446b1a","ef396111-e070-4066-96f4-762988c5625e","42be135c-fd61-44bd-899b-e042a16dfc9f","1ee1515d-d0e2-4cd5-94e0-8f98b2255e07","763b373b-ec6a-4674-a5ec-23d669741f9e","574a3625-98e6-49a1-a027-c2ac434584e6","29dc291e-8037-4113-85f5-d18cdba5526b","2d7bd09b-199e-48da-a0ce-142c9912adfc","82a03487-ea3a-45b4-b3bf-6bbb38ba0887","8276f75f-e3fe-4298-8c89-1a278c83682a","main"]}